README.md
setup.py
smartobject/__init__.py
smartobject/config.py
smartobject/constants.py
smartobject/factory.py
smartobject/smartobject.py
smartobject/storage.py
smartobject/sync.py
smartobject.egg-info/PKG-INFO
smartobject.egg-info/SOURCES.txt
smartobject.egg-info/dependency_links.txt
smartobject.egg-info/requires.txt
smartobject.egg-info/top_level.txt