Metadata-Version: 2.1
Name: smartobject
Version: 0.1.14
Summary: Smart Objects
Home-page: https://github.com/alttch/smartobject
Author: Altertech
Author-email: div@altertech.com
License: MIT
Platform: UNKNOWN
Classifier: Programming Language :: Python :: 3
Classifier: License :: OSI Approved :: MIT License
Classifier: Topic :: Software Development :: Libraries
